ai_harness/__init__.py
ai_harness/agents/Conversation.py
ai_harness/agents/DatasetAI.py
ai_harness/agents/JsonToJson.py
ai_harness/agents/PlaceMaking.py
ai_harness/agents/QaRetrieval.py
ai_harness/agents/QueryGenerator.py
ai_harness/agents/SiteAnalysis.py
ai_harness/agents/__init__.py
ai_harness/agents/utils/AppletResponse.py
ai_harness/agents/utils/RestWrapper.py
ai_harness/agents/utils/__init__.py
ai_harness/documents/__init__.py
ai_harness/documents/document.py
ai_harness_sdk-0.0.62.dist-info/METADATA
ai_harness_sdk-0.0.62.dist-info/WHEEL
ai_harness_sdk-0.0.62.dist-info/top_level.txt
ai_harness_sdk-0.0.62.dist-info/RECORD
