Metadata-Version: 2.1
Name: ai-harness-sdk
Version: 0.0.62
Summary: AI Harness SDK
Author: Navneet
Author-email: navneet@ai-harness.com
License: LICENSE
